{"mc":{
	"ming-sorrow":{
		"frameRate":24,
		"events":[
			
			],
		"frames":[
			
			{
			"res":"89B64253",
			"x":25,
			"y":25
			},
			{
			"res":"EDFA46AD",
			"x":26,
			"y":25
			},
			{
			"res":"CAD753BC",
			"x":26,
			"y":25
			},
			{
			"res":"E53FD146",
			"x":26,
			"y":25
			},
			{
			"res":"AF2106C7",
			"x":26,
			"y":25
			},
			{
			"res":"65CDCDBD",
			"x":26,
			"y":25
			},
			{
			"res":"FC68EE1D",
			"x":25,
			"y":25
			},
			{
			"res":"26730283",
			"x":25,
			"y":25
			},
			{
			"res":"C602049",
			"x":25,
			"y":25
			},
			{
			"res":"1F35586E",
			"x":25,
			"y":25
			},
			{
			"res":"25517792",
			"x":25,
			"y":25
			},
			{
			"res":"F34C774A",
			"x":25,
			"y":25
			},
			{
			"res":"AB80435F",
			"x":25,
			"y":25
			},
			{
			"res":"4F922106",
			"x":25,
			"y":25
			},
			{
			"res":"EA273180",
			"x":25,
			"y":25
			},
			{
			"res":"E1B33945",
			"x":25,
			"y":25
			},
			{
			"res":"87D9ED52",
			"x":25,
			"y":25
			},
			{
			"res":"90AF8FD5",
			"x":25,
			"y":25
			},
			{
			"res":"8531411C",
			"x":25,
			"y":25
			},
			{
			"res":"96A774A6",
			"x":25,
			"y":25
			},
			{
			"res":"25BCA89E",
			"x":25,
			"y":25
			},
			{
			"res":"FF59DCAF",
			"x":25,
			"y":25
			},
			{
			"res":"87A1F216",
			"x":25,
			"y":25
			},
			{
			"res":"9519BC41",
			"x":25,
			"y":25
			}
			]
}},
	"res":{
		"25517792":{"x":1,"y":1,"w":317,"h":370},
		"26730283":{"x":1595,"y":1,"w":316,"h":370},
		"9519BC41":{"x":1269,"y":745,"w":315,"h":370},
		"FC68EE1D":{"x":1,"y":373,"w":316,"h":370},
		"EDFA46AD":{"x":1,"y":745,"w":315,"h":370},
		"25BCA89E":{"x":635,"y":745,"w":315,"h":370},
		"AB80435F":{"x":319,"y":373,"w":316,"h":370},
		"87D9ED52":{"x":952,"y":1117,"w":315,"h":370},
		"65CDCDBD":{"x":1586,"y":1117,"w":314,"h":370},
		"96A774A6":{"x":1269,"y":1117,"w":315,"h":370},
		"E1B33945":{"x":955,"y":373,"w":315,"h":370},
		"87A1F216":{"x":1272,"y":373,"w":315,"h":370},
		"89B64253":{"x":1589,"y":373,"w":315,"h":370},
		"1F35586E":{"x":1277,"y":1,"w":316,"h":370},
		"AF2106C7":{"x":318,"y":745,"w":315,"h":370},
		"EA273180":{"x":320,"y":1,"w":317,"h":370},
		"FF59DCAF":{"x":952,"y":745,"w":315,"h":370},
		"C602049":{"x":639,"y":1,"w":317,"h":370},
		"E53FD146":{"x":1586,"y":745,"w":315,"h":370},
		"8531411C":{"x":1,"y":1117,"w":315,"h":370},
		"90AF8FD5":{"x":318,"y":1117,"w":315,"h":370},
		"CAD753BC":{"x":635,"y":1117,"w":315,"h":370},
		"F34C774A":{"x":958,"y":1,"w":317,"h":370},
		"4F922106":{"x":637,"y":373,"w":316,"h":370}
	}}